{
  "problem": {
    "dimension": 6,
    "n_bases": 5,
    "num_pairs": 10
  },
  "precision": {
    "dtype_name": "complex64"
  },
  "optimization": {
    "optimizer": "Adam",
    "steps": 2000,
    "learning_rate": 0.02,
    "init_scale": 0.05,
    "best_loss": 0.43903326988220215
  },
  "diagnostics": {
    "near_exact_tol": 1e-06,
    "num_near_exact_pairs": 0,
    "num_defective_pairs": 10,
    "max_unitarity_residual": 1.6679890677551157e-06,
    "mean_unitarity_residual": 1.192794979942846e-06
  },
  "environment": {
    "python_version": "3.11.14",
    "platform": "macOS-26.4.1-arm64-arm-64bit",
    "machine": "arm64",
    "processor": "arm",
    "torch_version": "2.11.0",
    "numpy_version": "2.3.5",
    "mps_built": true,
    "mps_available": true,
    "mps_detected": true,
    "reference_device": "cpu",
    "device_policy": "CPU reference execution. MPS availability is recorded, but the AMUB workflow requires torch.matrix_exp; previous local MPS execution did not support the required matrix-exponential kernel.",
    "session_timestamp": "20260529_165418",
    "output_root": "results_d6_amub_precision_campaign"
  },
  "run_tag": "d6_n5_complex64_seed0"
}